argdcls/__init__.py
argdcls/config.py
argdcls-0.5.0.dist-info/LICENSE
argdcls-0.5.0.dist-info/WHEEL
argdcls-0.5.0.dist-info/METADATA
argdcls-0.5.0.dist-info/RECORD
