Metadata-Version: 2.1
Name: argdcls
Version: 0.5.0
Summary: A simple tool to use dataclass as your config
Home-page: https://github.com/sotetsuk/argdcls
Author: Sotetsu KOYAMADA
Author-email: koyamada-s@sys.i.kyoto-u.ac.jp
Requires-Python: >=3.8,<4.0
Classifier: Programming Language :: Python :: 3
Classifier: Programming Language :: Python :: 3.10
Classifier: Programming Language :: Python :: 3.8
Classifier: Programming Language :: Python :: 3.9
Project-URL: Repository, https://github.com/sotetsuk/argdcls
